MANIFEST.in
README.md
setup.py
version
hashcat/__init__.py
hashcat/cli.py
hashcat.egg-info/PKG-INFO
hashcat.egg-info/SOURCES.txt
hashcat.egg-info/dependency_links.txt
hashcat.egg-info/entry_points.txt
hashcat.egg-info/requires.txt
hashcat.egg-info/top_level.txt
hashcat/hashcat/example.dict
hashcat/hashcat/example0.cmd
hashcat/hashcat/example0.hash
hashcat/hashcat/example0.sh
hashcat/hashcat/example400.cmd
hashcat/hashcat/example400.hash
hashcat/hashcat/example400.sh
hashcat/hashcat/example500.cmd
hashcat/hashcat/example500.hash
hashcat/hashcat/example500.sh
hashcat/hashcat/hashcat.hcstat2
hashcat/hashcat/hashcat.hctune
hashcat/hashcat/hashcat32.bin
hashcat/hashcat/hashcat32.exe
hashcat/hashcat/hashcat64.bin
hashcat/hashcat/hashcat64.exe
hashcat/hashcat/OpenCL/amp_a0.cl
hashcat/hashcat/OpenCL/amp_a1.cl
hashcat/hashcat/OpenCL/amp_a3.cl
hashcat/hashcat/OpenCL/inc_cipher_aes.cl
hashcat/hashcat/OpenCL/inc_cipher_camellia.cl
hashcat/hashcat/OpenCL/inc_cipher_kuznyechik.cl
hashcat/hashcat/OpenCL/inc_cipher_serpent.cl
hashcat/hashcat/OpenCL/inc_cipher_twofish.cl
hashcat/hashcat/OpenCL/inc_common.cl
hashcat/hashcat/OpenCL/inc_comp_multi.cl
hashcat/hashcat/OpenCL/inc_comp_multi_bs.cl
hashcat/hashcat/OpenCL/inc_comp_single.cl
hashcat/hashcat/OpenCL/inc_comp_single_bs.cl
hashcat/hashcat/OpenCL/inc_hash_constants.h
hashcat/hashcat/OpenCL/inc_hash_functions.cl
hashcat/hashcat/OpenCL/inc_hash_md4.cl
hashcat/hashcat/OpenCL/inc_hash_md5.cl
hashcat/hashcat/OpenCL/inc_hash_ripemd160.cl
hashcat/hashcat/OpenCL/inc_hash_sha1.cl
hashcat/hashcat/OpenCL/inc_hash_sha224.cl
hashcat/hashcat/OpenCL/inc_hash_sha256.cl
hashcat/hashcat/OpenCL/inc_hash_sha384.cl
hashcat/hashcat/OpenCL/inc_hash_sha512.cl
hashcat/hashcat/OpenCL/inc_hash_streebog256.cl
hashcat/hashcat/OpenCL/inc_hash_streebog512.cl
hashcat/hashcat/OpenCL/inc_hash_whirlpool.cl
hashcat/hashcat/OpenCL/inc_luks_aes.cl
hashcat/hashcat/OpenCL/inc_luks_af.cl
hashcat/hashcat/OpenCL/inc_luks_essiv.cl
hashcat/hashcat/OpenCL/inc_luks_serpent.cl
hashcat/hashcat/OpenCL/inc_luks_twofish.cl
hashcat/hashcat/OpenCL/inc_luks_xts.cl
hashcat/hashcat/OpenCL/inc_rp.cl
hashcat/hashcat/OpenCL/inc_rp.h
