Metadata-Version: 2.1
Name: hashcat
Version: 5.1.0.post2
Summary: Python pip installer for hashcat
Home-page: https://github.com/bannsec/hashcat
Author: Michael Bann
Author-email: self@bannsecurity.com
License: MIT
Keywords: hashcat
Platform: UNKNOWN
Classifier: Intended Audience :: End Users/Desktop
Classifier: License :: OSI Approved :: MIT License
Classifier: Operating System :: POSIX :: Linux
Classifier: Environment :: Console
Provides-Extra: dev
